ancestralcost/__init__.py
ancestralcost/__main__.py
ancestralcost/alignment_permutations.py
ancestralcost/ancestralcost.py
ancestralcost/graph.py
ancestralcost/indel_placement.py
ancestralcost/oldmain.py
ancestralcost/tree_code.py
ancestralcost-1.0.1.data/data/LICENSE
ancestralcost-1.0.1.dist-info/LICENSE
ancestralcost-1.0.1.dist-info/METADATA
ancestralcost-1.0.1.dist-info/WHEEL
ancestralcost-1.0.1.dist-info/entry_points.txt
ancestralcost-1.0.1.dist-info/top_level.txt
ancestralcost-1.0.1.dist-info/RECORD
