Metadata-Version: 2.1
Name: ancestralcost
Version: 1.0.1
Summary: UNKNOWN
Home-page: https://github.com/gabefoley/ancestralcost
Author: Gabe Foley
Author-email: g.foley@uq.edu.au
License: GPL3
Project-URL: Bug Tracker, https://github.com/gabefoley/ancestralcost/issues
Project-URL: Documentation, https://github.com/gabefoley/ancestralcost
Project-URL: Source Code, https://github.com/gabefoley/ancestralcost
Keywords: ancestral sequence reconstruction,phylogenetics,ancestors
Platform: UNKNOWN
Classifier: Development Status :: 5 - Production/Stable
Classifier: Intended Audience :: Science/Research
Classifier: License :: OSI Approved :: GNU General Public License v3 (GPLv3)
Classifier: Natural Language :: English
Classifier: Operating System :: OS Independent
Classifier: Programming Language :: Python :: 3.6
Classifier: Programming Language :: Python :: 3.7
Classifier: Programming Language :: Python :: 3.8
Classifier: Topic :: Scientific/Engineering :: Bio-Informatics
Requires-Python: >=3.6
License-File: LICENSE
Requires-Dist: pandas
Requires-Dist: numpy
Requires-Dist: ete3
Requires-Dist: pyqt5
